{
    "actionOnStepFail": null, 
    "concurrency": 1, 
    "enabled": true, 
    "externalUuid4": "085c0e71-c7ad-47ff-8b8c-37dae875708b", 
    "isBlueprint": true, 
    "key": "refreshdropboxaccesstoken", 
    "links": [
        {
            "order": 50, 
            "stepKey": "rdatcreateaccesstokendirectory"
        }, 
        {
            "order": 100, 
            "stepKey": "rdatrefreshdropboxaccesstoken"
        }
    ], 
    "name": "Refresh Dropbox Access Token", 
    "type": "com.servertribe.attune.tuples.StepGroupTuple"
}